Metadata-Version: 2.1
Name: RejQ.py
Version: 1.0
Summary: Library powered by rejQ
Home-page: https://github.com/TheeeWhiteDeath
Download-URL: https://github.com/TheeeWhiteDeath
Author: rejQ
Author-email: rejq1akk@gmail.com
License: MIT
Keywords: rejQ.py,rejQ,rejQ-py,rejQ-bot,api,python,python3,python3.x,rejQ,official,async,sync,rejQ
License-File: LICENSE
